circadipy/__init__.py
circadipy/chrono_plotter.py
circadipy/chrono_reader.py
circadipy/chrono_rhythm.py
circadipy/chrono_simulation.py
circadipy/tutorial_pipeline.ipynb
circadipy-0.1.11.dist-info/LICENSE
circadipy-0.1.11.dist-info/METADATA
circadipy-0.1.11.dist-info/WHEEL
circadipy-0.1.11.dist-info/top_level.txt
circadipy-0.1.11.dist-info/zip-safe
circadipy-0.1.11.dist-info/RECORD
