Metadata-Version: 2.1
Name: circadipy
Version: 0.1.11
Summary: Tool for analyzing and visualizing circadian cycle data
Home-page: https://github.com/mcjpedro/circadipy
Author: João Pedro Carvalho Moreira
Author-email: mcjpedro@gmail.com
Keywords: circadian,chronobiology,data
License-File: LICENSE
Requires-Dist: collection==0.1.6
Requires-Dist: CosinorPy==3.0
Requires-Dist: matplotlib==3.6.2
Requires-Dist: matplotlib-inline==0.1.6
Requires-Dist: numpy==1.22.0
Requires-Dist: openpyxl==3.0.10
Requires-Dist: pandas==1.5.2
Requires-Dist: pillow==9.4.0
Requires-Dist: pymice==1.1.0
Requires-Dist: seaborn==0.13.0
Requires-Dist: scikit-learn==1.2.0
Requires-Dist: scikit-optimize==0.9.0
Requires-Dist: scipy==1.10.0
Requires-Dist: PyQt5==5.15.10
Requires-Dist: notebook==7.1.3
Requires-Dist: nbsphinx==0.9.3
Requires-Dist: sphinx-rtd-theme==2.0.0
Requires-Dist: ipykernel==6.29.4
